Metadata-Version: 2.4
Name: adafruit-circuitpython-display-analogclock
Version: 1.0.1
Summary: Draw a traditional 12-hour analog clock face with hour and minute hands. Allows you to provide graphics to customize the clock.
Author-email: Adafruit Industries <circuitpython@adafruit.com>
License: MIT
Project-URL: Homepage, https://github.com/adafruit/Adafruit_CircuitPython_Display_AnalogClock
Keywords: adafruit,blinka,circuitpython,micropython,display_analogclock,clock,clockface,analog,analogclock,analogclockface,time,hours,minutes
Classifier: Intended Audience :: Developers
Classifier: Topic :: Software Development :: Libraries
Classifier: Topic :: Software Development :: Embedded Systems
Classifier: Topic :: System :: Hardware
Classifier: License :: OSI Approved :: MIT License
Classifier: Programming Language :: Python :: 3
License-File: LICENSE
Requires-Dist: Adafruit-Blinka
Requires-Dist: adafruit-circuitpython-display-text
Requires-Dist: adafruit-circuitpython-anchored-tilegrid
Requires-Dist: adafruit-circuitpython-imageload
Provides-Extra: optional
Dynamic: license-file
